tourscraper/__init__.py
tourscraper/app.py
tourscraper-0.1.0.dist-info/entry_points.txt
tourscraper-0.1.0.dist-info/LICENSE
tourscraper-0.1.0.dist-info/WHEEL
tourscraper-0.1.0.dist-info/METADATA
tourscraper-0.1.0.dist-info/RECORD
