Metadata-Version: 2.1
Name: tourscraper
Version: 0.1.0
Summary: Web scraper that aggregates tour dates in desired cities
Author: Dalton Black
Author-email: projectdjswag@gmail.com
Requires-Python: >=3.8,<4.0
Classifier: Programming Language :: Python :: 3
Classifier: Programming Language :: Python :: 3.10
Classifier: Programming Language :: Python :: 3.8
Classifier: Programming Language :: Python :: 3.9
Requires-Dist: click (>=8.0.4,<9.0.0)
Requires-Dist: python-dotenv (>=0.20.0,<0.21.0)
Requires-Dist: selenium (>=4.1.3,<5.0.0)
